clearskies_auth_server/__init__.py
clearskies_auth_server/applications/__init__.py
clearskies_auth_server/applications/key_manager.py
clearskies_auth_server/authentication/__init__.py
clearskies_auth_server/authentication/jwks_direct.py
clearskies_auth_server/column_types/__init__.py
clearskies_auth_server/column_types/multi_tenant_configuration.py
clearskies_auth_server/column_types/password.py
clearskies_auth_server/column_types/tenant_id.py
clearskies_auth_server/di/__init__.py
clearskies_auth_server/di/me.py
clearskies_auth_server/handlers/__init__.py
clearskies_auth_server/handlers/create_key.py
clearskies_auth_server/handlers/delete_key.py
clearskies_auth_server/handlers/delete_not_self.py
clearskies_auth_server/handlers/delete_oldest_key.py
clearskies_auth_server/handlers/jwks.py
clearskies_auth_server/handlers/key_base.py
clearskies_auth_server/handlers/key_base_test_helper.py
clearskies_auth_server/handlers/list_keys.py
clearskies_auth_server/handlers/password_less_email_request_login.py
clearskies_auth_server/handlers/password_less_link_login.py
clearskies_auth_server/handlers/password_login.py
clearskies_auth_server/handlers/password_reset.py
clearskies_auth_server/handlers/password_reset_request.py
clearskies_auth_server/handlers/profile.py
clearskies_auth_server/handlers/profile_get.py
clearskies_auth_server/handlers/profile_update.py
clearskies_auth_server/handlers/switch_tenant.py
clearskies_auth_server/input_requirements/__init__.py
clearskies_auth_server/input_requirements/have_i_been_pwned.py
clearskies_auth_server/input_requirements/letters_digits.py
clearskies_auth_server/input_requirements/letters_digits_special_characters.py
clearskies_auth_server/input_requirements/password_validation.py
clear_skies_auth_server-0.12.11.dist-info/LICENSE
clear_skies_auth_server-0.12.11.dist-info/METADATA
clear_skies_auth_server-0.12.11.dist-info/WHEEL
clear_skies_auth_server-0.12.11.dist-info/RECORD
