Metadata-Version: 2.1
Name: clear-skies-auth-server
Version: 0.12.11
Summary: clearskies bindings for managing an authentication server that issues JWTs
Home-page: https://github.com/cmancone/clearskies-auth-server
License: MIT
Author: Conor Mancone
Author-email: cmancone@gmail.com
Requires-Python: >=3.10,<4.0
Classifier: Development Status :: 4 - Beta
Classifier: Intended Audience :: Developers
Classifier: License :: OSI Approved :: MIT License
Classifier: Programming Language :: Python :: 3
Classifier: Programming Language :: Python :: 3.10
Classifier: Programming Language :: Python :: 3.11
Requires-Dist: argon2-cffi (>=21.3.0,<22.0.0)
Requires-Dist: clear-skies (>=1.17.1,<2.0.0)
Requires-Dist: jwcrypto (>=1.5.0,<2.0.0)
Requires-Dist: passlib (>=1.7.4,<2.0.0)
Requires-Dist: python-jose (>=3.3.0,<4.0.0)
Project-URL: Repository, https://github.com/cmancone/clearskies-auth-server
